{"name":"Header Group","type":"header","sections":{"announcement-bar":{"type":"announcement-bar","settings":{"show_announcement_bar":true,"heading":"Welcome to our store","link":"","color_bg":"linear-gradient(335deg, rgba(125, 126, 128, 1) 3%, rgba(8, 8, 8, 1) 87%)","color_text":"#ffffff","font_style":"body","font_bold":false}},"header":{"type":"header","settings":{"header_logo_position":"middle-left","enable_sticky_header":true,"transparent_header":false,"header_menu":"main-menu","header_menu_font":"body","header_bold_links":false,"mega_menu_title_font":"body"}},"menu-drawer":{"type":"menu-drawer","settings":{"mobile_menu":"main-menu","mobile_menu_text":"<p>Address and phone number<\/p>","mobile_menu_show_socials":true,"mobile_menu_drawer_style":"quinary"}},"cart-drawer":{"type":"cart-drawer","settings":{}}},"order":["announcement-bar","header","menu-drawer","cart-drawer"]}